{
  "domainKey": "tealhq.com",
  "title": "Resume & Job Search Tools: Land Interviews 6x Faster",
  "sourceUrl": "https://www.tealhq.com/",
  "capturedAt": "2026-05-31T07:06:37.088Z",
  "keywords": [
    "job-search",
    "resume-builder",
    "career-tools",
    "ats-friendly",
    "job-tracker",
    "resume-templates",
    "modern",
    "professional",
    "saas",
    "hero",
    "carousel",
    "testimonial",
    "pricing",
    "card",
    "navigation"
  ],
  "pageType": "saas marketing",
  "categories": [
    "technology",
    "human-resources",
    "career-development",
    "saas"
  ]
}